washpy/__init__.py
washpy/authenticate.py
washpy/device.py
washpy/device_user.py
washpy/pExtended.py
washpy/permission.py
washpy/post_new_password.py
washpy/role.py
washpy/state.py
washpy/status.py
washpy/user.py
washpy-0.6.0.dist-info/LICENSE
washpy-0.6.0.dist-info/METADATA
washpy-0.6.0.dist-info/WHEEL
washpy-0.6.0.dist-info/RECORD
