Metadata-Version: 2.1
Name: washpy
Version: 0.6.0
Summary: A partial implementation of the Miele Professional IP Profile API
Home-page: https://codeberg.org/johann-cm/washpy
License: LGPL-3.0-only
Author: Johann Carl Meyer
Author-email: info@johannc.de
Requires-Python: >=3.10,<4.0
Classifier: License :: OSI Approved :: GNU Lesser General Public License v3 (LGPLv3)
Classifier: Programming Language :: Python :: 3
Classifier: Programming Language :: Python :: 3.10
Classifier: Programming Language :: Python :: 3.11
Classifier: Programming Language :: Python :: 3.12
Requires-Dist: isodate (>=0.6.1,<0.7.0)
Requires-Dist: pydantic (>=2.7.1,<3.0.0)
Requires-Dist: requests (==2.29.0)
Project-URL: Documentation, https://johann-cm.codeberg.page/washpy/washpy.html
Project-URL: Repository, https://codeberg.org/johann-cm/washpy
